clixx/__init__.py
clixx/_rich.py
clixx/arguments.py
clixx/commands.py
clixx/constants.py
clixx/decorators.py
clixx/exceptions.py
clixx/groups.py
clixx/parsers.py
clixx/printers.py
clixx/py.typed
clixx/types.py
clixx-0.9.0a0.dist-info/LICENSE
clixx-0.9.0a0.dist-info/METADATA
clixx-0.9.0a0.dist-info/WHEEL
clixx-0.9.0a0.dist-info/top_level.txt
clixx-0.9.0a0.dist-info/zip-safe
clixx-0.9.0a0.dist-info/RECORD
