Metadata-Version: 2.1
Name: clixx
Version: 0.9.0a0
Summary: Command-line interface parser & framework for Python
Home-page: https://github.com/xymy/clixx
Author: xymy
Author-email: thyfan@163.com
Maintainer: xymy
Maintainer-email: thyfan@163.com
License: MIT
Project-URL: Documentation, https://github.com/xymy/clixx
Project-URL: Issue Tracker, https://github.com/xymy/clixx/issues
Project-URL: Source Code, https://github.com/xymy/clixx
Keywords: cli
Classifier: Development Status :: 3 - Alpha
Classifier: Intended Audience :: Developers
Classifier: License :: OSI Approved
Classifier: License :: OSI Approved :: MIT License
Classifier: Operating System :: OS Independent
Classifier: Programming Language :: Python
Classifier: Programming Language :: Python :: 3
Classifier: Programming Language :: Python :: 3 :: Only
Classifier: Programming Language :: Python :: 3.8
Classifier: Programming Language :: Python :: 3.9
Classifier: Programming Language :: Python :: 3.10
Classifier: Programming Language :: Python :: 3.11
Classifier: Topic :: Software Development
Classifier: Topic :: Software Development :: Libraries
Requires-Python: >=3.8
License-File: LICENSE
Requires-Dist: rich (>=13.0)
Requires-Dist: typing-extensions (>=4.4)
Provides-Extra: lint
Requires-Dist: black (>=23.7) ; extra == 'lint'
Requires-Dist: ruff (>=0.0.280) ; extra == 'lint'
Requires-Dist: mypy (>=1.4) ; extra == 'lint'
Provides-Extra: test
Requires-Dist: coverage (>=7.2) ; extra == 'test'
Requires-Dist: hypothesis (>=6.80) ; extra == 'test'
Requires-Dist: pytest (>=7.4) ; extra == 'test'
Requires-Dist: pytest-cov (>=4.1) ; extra == 'test'
